standard_transform/__init__.py
standard_transform/base.py
standard_transform/datasets.py
standard_transform/streamlines.py
standard_transform/utils.py
standard_transform/data/minnie_um_streamline.json
standard_transform/data/v1dd_um_streamline.json
standard_transform-1.4.1.dist-info/METADATA
standard_transform-1.4.1.dist-info/WHEEL
standard_transform-1.4.1.dist-info/licenses/LICENSE
standard_transform-1.4.1.dist-info/RECORD
