Metadata-Version: 2.4
Name: standard-transform
Version: 1.4.1
Summary: Define and repeat basic affine transformation tasks for datasets
Project-URL: Homepage, https://github.com/ceesem/standard_transform
Project-URL: Repository, https://github.com/ceesem/standard_transform
Author-email: Casey Schneider-Mizell <caseys@alleninstitute.org>
License: MIT License
License-File: LICENSE
Classifier: Development Status :: 4 - Beta
Classifier: Intended Audience :: Science/Research
Classifier: License :: OSI Approved :: MIT License
Classifier: Programming Language :: Python :: 3
Classifier: Programming Language :: Python :: 3.10
Classifier: Programming Language :: Python :: 3.11
Classifier: Programming Language :: Python :: 3.12
Requires-Python: >=3.10
Requires-Dist: numpy
Requires-Dist: pandas
Requires-Dist: scipy
